{
    "version": 3,
    "configurePresets": [
        {
          "name": "windows-base",
          "hidden": true,
          "generator": "Ninja",
          "binaryDir": "${sourceDir}/out/build/${presetName}",
          "installDir": "${sourceDir}/out/install/${presetName}",
          "cacheVariables": {
          },
          "condition": {
            "type": "equals",
            "lhs": "${hostSystemName}",
            "rhs": "Windows"
          }
        },
        {
          "name": "i686-elf",
          "hidden": false,
          "generator": "Ninja",
          "binaryDir": "${sourceDir}/out/build/${presetName}",
          "installDir": "${sourceDir}/out/install/${presetName}",
          "cacheVariables": {
            "CMAKE_BUILD_TYPE": "Debug",
            "LINKER_SCRIPT": "kernel/linker.ld",
            "OUTPUT_DIR": "C:/Users/omark/Documents/obos/out/",
            "CMAKE_C_COMPILER": "i686-elf-gcc",
            "CMAKE_ASM_COMPILER": "i686-elf-gcc",
            "CMAKE_ASM-ATT_COMPILER": "i686-elf-gcc",
            "CMAKE_NASM_COMPILER": "nasm",
            "CMAKE_C_COMPILER_WORKS": "true",
            "CMAKE_ASM_COMPILER_WORKS": "true",
            "CMAKE_ASM-ATT_COMPILER_WORKS": "true",
            "CMAKE_NASM_COMPILER_WORKS": "true",
            "CMAKE_SYSTEM_NAME": "Generic",
            "CMAKE_SYSTEM_PROCESSOR": "i686",
            "CMAKE_FIND_ROOT_PATH_MODE_LIBRARY": "ONLY",
            "CMAKE_FIND_ROOT_PATH_MODE_INCLUDE": "ONLY",
            "CMAKE_FIND_ROOT_PATH_MODE_PROGRAM": "NEVER"
          },
          "condition": {
            "type": "equals",
            "lhs": "${hostSystemName}",
            "rhs": "Windows"
          }
        },
        {
            "name": "x64-debug",
            "displayName": "x64 Debug",
            "inherits": "windows-base",
            "architecture": {
                "value": "x64",
                "strategy": "external"
            },
            "cacheVariables": {
                "CMAKE_BUILD_TYPE": "Debug"
            }
        },
        {
            "name": "x64-release",
            "displayName": "x64 Release",
            "inherits": "x64-debug",
            "cacheVariables": {
                "CMAKE_BUILD_TYPE": "Release"
            }
        },
        {
            "name": "x86-debug",
            "displayName": "x86 Debug",
            "inherits": "windows-base",
            "architecture": {
                "value": "x86",
                "strategy": "external"
            },
            "cacheVariables": {
                "CMAKE_BUILD_TYPE": "Debug"
            }
        },
        {
            "name": "x86-release",
            "displayName": "x86 Release",
            "inherits": "x86-debug",
            "cacheVariables": {
                "CMAKE_BUILD_TYPE": "Release"
            }
        },
        {
            "name": "linux-debug",
            "displayName": "Linux Debug",
            "generator": "Ninja",
            "binaryDir": "${sourceDir}/out/build/${presetName}",
            "installDir": "${sourceDir}/out/install/${presetName}",
            "cacheVariables": {
              "CMAKE_BUILD_TYPE": "Debug",
              "LINKER_SCRIPT": "scripts/linker.ld",
              "OUTPUT_DIR": "/mnt/c/Code/obos/out/",
              "CRTBEGIN_DIRECTORY": "/home/omar/opt/cross/lib/gcc/i686-elf/11.4.0"
            },
            "condition": {
                "type": "equals",
                "lhs": "${hostSystemName}",
                "rhs": "Linux"
            },
            "vendor": {
                "microsoft.com/VisualStudioRemoteSettings/CMake/1.0": {
                    "sourceDir": "$env{HOME}/.vs/$ms{projectDirName}"
                }
            }
        },
        {
            "name": "macos-debug",
            "displayName": "macOS Debug",
            "generator": "Ninja",
            "binaryDir": "${sourceDir}/out/build/${presetName}",
            "installDir": "${sourceDir}/out/install/${presetName}",
            "cacheVariables": {
                "CMAKE_BUILD_TYPE": "Debug"
            },
            "condition": {
                "type": "equals",
                "lhs": "${hostSystemName}",
                "rhs": "Darwin"
            },
            "vendor": {
                "microsoft.com/VisualStudioRemoteSettings/CMake/1.0": {
                    "sourceDir": "$env{HOME}/.vs/$ms{projectDirName}"
                }
            }
        }
    ]
}
